{
  "version": "0.8.3",
  "description": "Web3MQ's Snap",
  "proposedName": "Web3MQ Snap",
  "repository": {
    "type": "git",
    "url": "https://github.com/MetaMask/template-snap-monorepo.git"
  },
  "source": {
    "shasum": "YlPJ+RjeIrMqXCNHwKiDjk1mojXjlPu/gK1ndZyiHAM=",
    "location": {
      "npm": {
        "filePath": "dist/bundle.js",
        "iconPath": "images/icon.svg",
        "packageName": "@web3mq/snap",
        "registry": "https://registry.npmjs.org/"
      }
    }
  },
  "initialPermissions": {
    "snap_notify": {},
    "snap_dialog": {},
    "snap_manageState": {},
    "endowment:long-running": {},
    "endowment:ethereum-provider": {},
    "endowment:network-access": {},
    "endowment:rpc": {
      "dapps": true,
      "snaps": false
    }
  },
  "manifestVersion": "0.1"
}
